Classfile /Users/hoshito/java/jjuc_night_sample/Test.class
  Last modified 2015/04/26; size 355 bytes
  MD5 checksum 6f61450bacf8b7885b349def89272601
  Compiled from "Test.java"
public class Test
  minor version: 0
  major version: 52
  flags: ACC_PUBLIC, ACC_SUPER
Constant pool:
   #1 = Methodref          #5.#16         // java/lang/Object."<init>":()V
   #2 = Class              #17            // Test
   #3 = Methodref          #2.#16         // Test."<init>":()V
   #4 = Methodref          #2.#18         // Test.add:(II)I
   #5 = Class              #19            // java/lang/Object
   #6 = Utf8               <init>
   #7 = Utf8               ()V
   #8 = Utf8               Code
   #9 = Utf8               LineNumberTable
  #10 = Utf8               add
  #11 = Utf8               (II)I
  #12 = Utf8               main
  #13 = Utf8               ([Ljava/lang/String;)V
  #14 = Utf8               SourceFile
  #15 = Utf8               Test.java
  #16 = NameAndType        #6:#7          // "<init>":()V
  #17 = Utf8               Test
  #18 = NameAndType        #10:#11        // add:(II)I
  #19 = Utf8               java/lang/Object
{
  public Test();
    descriptor: ()V
    flags: ACC_PUBLIC
    Code:
      stack=1, locals=1, args_size=1
         0: aload_0
         1: invokespecial #1                  // Method java/lang/Object."<init>":()V
         4: return
      LineNumberTable:
        line 1: 0

  private int add(int, int);
    descriptor: (II)I
    flags: ACC_PRIVATE
    Code:
      stack=2, locals=4, args_size=3
         0: iload_1
         1: iload_2
         2: iadd
         3: istore_3
         4: iload_3
         5: ireturn
      LineNumberTable:
        line 3: 0
        line 4: 4

  public static void main(java.lang.String...);
    descriptor: ([Ljava/lang/String;)V
    flags: ACC_PUBLIC, ACC_STATIC, ACC_VARARGS
    Code:
      stack=3, locals=3, args_size=1
         0: new           #2                  // class Test
         3: dup
         4: invokespecial #3                  // Method "<init>":()V
         7: astore_1
         8: aload_1
         9: bipush        10
        11: bipush        20
        13: invokespecial #4                  // Method add:(II)I
        16: istore_2
        17: return
      LineNumberTable:
        line 7: 0
        line 8: 8
        line 9: 17
}
SourceFile: "Test.java"
